bigquery_schema_coerce/__init__.py
bigquery_schema_coerce/core.py
bigquery_schema_coerce/types/__init__.py
bigquery_schema_coerce/types/bool.py
bigquery_schema_coerce/types/float.py
bigquery_schema_coerce/types/int.py
bigquery_schema_coerce/types/string.py
bigquery_schema_coerce/types/timestamp.py
tests/__init__.py
tests/test_core.py
tests/types/__init__.py
tests/types/test_bool.py
tests/types/test_float.py
tests/types/test_int.py
tests/types/test_string.py
tests/types/test_timestamp.py
bigquery_schema_coerce-1.2.0.dist-info/LICENSE
bigquery_schema_coerce-1.2.0.dist-info/METADATA
bigquery_schema_coerce-1.2.0.dist-info/WHEEL
bigquery_schema_coerce-1.2.0.dist-info/top_level.txt
bigquery_schema_coerce-1.2.0.dist-info/zip-safe
bigquery_schema_coerce-1.2.0.dist-info/RECORD
