Metadata-Version: 2.1
Name: bigquery-schema-coerce
Version: 1.2.0
Summary: Force python dictionary to type convert and project onto the given schema
Home-page: UNKNOWN
Author: Jon Robison
Author-email: narfman0@gmail.com
License: LICENSE
Keywords: bigquery-schema-coerce
Platform: UNKNOWN
Classifier: Development Status :: 4 - Beta
Classifier: License :: OSI Approved :: GNU General Public License v3 (GPLv3)
Classifier: Operating System :: OS Independent
Classifier: Programming Language :: Python
Classifier: Topic :: Software Development :: Libraries :: Python Modules
Requires-Dist: google-cloud-bigquery
Requires-Dist: python-dateutil
